MANIFEST.in
NAME
VERSION
setup.py
pyBaseX.egg-info/PKG-INFO
pyBaseX.egg-info/SOURCES.txt
pyBaseX.egg-info/dependency_links.txt
pyBaseX.egg-info/requires.txt
pyBaseX.egg-info/top_level.txt
pybasex/__init__.py
pybasex/basex_client.py
pybasex/errors.py
pybasex/fragments.py
pybasex/utils/__init__.py
pybasex/utils/xml_utils.py
test/__init__.py
test/pybasex/__init__.py
test/pybasex/test_basex_client.py